Metadata-Version: 2.1
Name: fortifysql
Version: 0.4.0
Summary: SQLite extension with a focus on security
Author: Archie Hickmott
Author-email: 25hickmar@gmail.com
Project-URL: Bug Reports, https://github.com/ArchieHickmott/fortify-sql
Project-URL: Documentation, https://archiehickmott.github.io/fortify-sql/
Keywords: sql,security
Classifier: Intended Audience :: Developers
Classifier: Development Status :: 4 - Beta
License-File: LICENSE
Requires-Dist: sqlparse
